weather_api/__init__.py
weather_api/api_helper.py
weather_api/configuration.py
weather_api/decorators.py
weather_api/weather_api_client.py
weather_api/controllers/__init__.py
weather_api/controllers/base_controller.py
weather_api/controllers/find_weather_controller.py
weather_api/exceptions/__init__.py
weather_api/exceptions/api_exception.py
weather_api/http/__init__.py
weather_api/http/http_call_back.py
weather_api/http/http_client.py
weather_api/http/http_context.py
weather_api/http/http_method_enum.py
weather_api/http/http_request.py
weather_api/http/http_response.py
weather_api/http/requests_client.py
weather_api/http/auth/__init__.py
weather_api/http/auth/custom_query_auth.py
weather_api/models/__init__.py
weather_api/models/city_weather.py
weather_api/models/clouds.py
weather_api/models/coord.py
weather_api/models/list.py
weather_api/models/main.py
weather_api/models/rain.py
weather_api/models/sys.py
weather_api/models/weather.py
weather_api/models/wind.py
weather_api-1.0.dist-info/LICENSE
weather_api-1.0.dist-info/METADATA
weather_api-1.0.dist-info/WHEEL
weather_api-1.0.dist-info/top_level.txt
weather_api-1.0.dist-info/RECORD
