Metadata-Version: 2.1
Name: weather_api
Version: 1.0
Summary: This is the new API for weather forecasting.
Home-page: https://apimatic.io
Author: APIMatic SDK Generator
Author-email: support@apimatic.io
License: UNKNOWN
Platform: UNKNOWN
